Simulation/Verilog/LogicCircuits/ALU/salu/salu.v
//Simple ALU
//`timescale 1ns/100ps
module salu(operanda,operandb,mux,result);
    
    //inputs,outputs and wires
    input [7:0] operanda,operandb;
    input [3:0] mux;
    output [7:0] result;
    wire [7:0] op1,op2;
    reg [7:0] r;

    parameter [3:0] Add = 4'h0,
                    Sub = 4'h1,
                    Mul = 4'h2,
                    Div = 4'h3,
                    Not = 4'h4,
                    And = 4'h5,
                    Or  = 4'h6,
                    Nand= 4'h7,
                    Nor = 4'h8,
                    Xor = 4'h9,
                    Shtl= 4'ha,
                    Shtr= 4'hb;

    //variables for operations
    assign op1 = operanda;
    assign op2 = operandb;
    //Assign the output 
    assign result = r;

    always @(mux or op1 or op2)
    begin
        case (mux)
         Add : r = op1 + op2;    //Add
         Sub : r = op1 - op2;    //Sub
         Mul : r = op1 * op2;    //Mul
         Div : r = op1 / op2;    //Div
         Not : r = ~op1;         //NOT
         And : r = op1 & op2;    //AND
         Or  : r = op1 | op2;    //OR
         Nand: r = ~(op1 & op2); //NAND 
         Nor : r = ~(op1 | op2); //NOR                
         Xor : r = op1 ^ op2;    //XOR
         Shtl: r = op1 << 1;     //Logical shift left
         Shtr: r = op1 >> 1;     //Logical shift right
        endcase 
    end
    
endmodule

Simulation/Verilog/LogicCircuits/ALU/salu/salu_tb.v
module salu_tb;

    // Inputs
    reg [7:0] opA;
    reg [7:0] opB;
    reg [3:0] Mux;

    // Outputs
    wire [7:0] Result;

    // testing salu
    salu SALU ( .operanda(opA), .operandb(opB), .mux(Mux), .result(Result));

    initial begin
      $dumpfile("wave.vcd");
      $dumpvars(); 
      $monitor("simtime=%g,opA=%b,opB=%b,Mux=%h,Result=%b",$time,opA,opB,Mux,Result);
      // Apply inputs.
        opA = 8'b01101010;
        opB = 8'b00111011;
        // Multiplex
        Mux = 'h0; #10;
        Mux = 'h1; #10;
        Mux = 'h2; #10;
        Mux = 'h3; #10;
        Mux = 'h4; #10;
        Mux = 'h5; #10;
        Mux = 'h6; #10;
        Mux = 'h7; #10;
        Mux = 'h8; #10;
        Mux = 'h9; #10;
        Mux = 'hA; #10;
        Mux = 'hB; #10;
    end
      
endmodule

Simulation/Verilog/LogicCircuits/ALU/salu/wave.vcd
$date
	Sun May 15 11:40:08 2022
$end
$version
	Icarus Verilog
$end
$timescale
	1s
$end
$scope module salu_tb $end
$var wire 8 ! Result [7:0] $end
$var reg 4 " Mux [3:0] $end
$var reg 8 # opA [7:0] $end
$var reg 8 $ opB [7:0] $end
$scope module SALU $end
$var wire 4 % mux [3:0] $end
$var wire 8 & op1 [7:0] $end
$var wire 8 ' op2 [7:0] $end
$var wire 8 ( operanda [7:0] $end
$var wire 8 ) operandb [7:0] $end
$var wire 8 * result [7:0] $end
$var reg 8 + r [7:0] $end
$upscope $end
$upscope $end
$enddefinitions $end
#0
$dumpvars
b10100101 +
b10100101 *
b111011 )
b1101010 (
b111011 '
b1101010 &
b0 %
b111011 $
b1101010 #
b0 "
b10100101 !
$end
#10
b101111 !
b101111 *
b101111 +
b1 "
b1 %
#20
b1101110 !
b1101110 *
b1101110 +
b10 "
b10 %
#30
b1 !
b1 *
b1 +
b11 "
b11 %
#40
b10010101 !
b10010101 *
b10010101 +
b100 "
b100 %
#50
b101010 !
b101010 *
b101010 +
b101 "
b101 %
#60
b1111011 !
b1111011 *
b1111011 +
b110 "
b110 %
#70
b11010101 !
b11010101 *
b11010101 +
b111 "
b111 %
#80
b10000100 !
b10000100 *
b10000100 +
b1000 "
b1000 %
#90
b1010001 !
b1010001 *
b1010001 +
b1001 "
b1001 %
#100
b11010100 !
b11010100 *
b11010100 +
b1010 "
b1010 %
#110
b110101 !
b110101 *
b110101 +
b1011 "
b1011 %
